common/__init__.py
common/banner.py
common/colors.py
common/output_wr.py
common/requestUp.py
common/threading.py
common/uriParser.py
modules/__init__.py
modules/dnsLookup.py
modules/dorkTable.py
modules/dorksEngine.py
modules/druExploits.py
modules/jooExploits.py
modules/jooGrabber.py
modules/portChecker.py
modules/prestaExploits.py
modules/wpExploits.py
modules/wpGrabber.py
vulnx-1.6.dist-info/LICENSE
vulnx-1.6.dist-info/METADATA
vulnx-1.6.dist-info/WHEEL
vulnx-1.6.dist-info/top_level.txt
vulnx-1.6.dist-info/RECORD
