Metadata-Version: 2.1
Name: vulnx
Version: 1.6
Summary: vulnx is a cms and vulnerabilites detection, an intelligent auto shell injector
Home-page: https://github.com/anouarbensaad/vulnx
Author: anouarbensaad
Author-email: bensaad.tig@gmail.com
License: UNKNOWN
Platform: UNKNOWN
Classifier: Programming Language :: Python :: 3
Classifier: License :: OSI Approved :: MIT License
Classifier: Operating System :: OS Independent
